yomifreq/__init__.py
yomifreq/yomifreq.py
yomifreq-0.1.1b0.dist-info/METADATA
yomifreq-0.1.1b0.dist-info/WHEEL
yomifreq-0.1.1b0.dist-info/entry_points.txt
yomifreq-0.1.1b0.dist-info/top_level.txt
yomifreq-0.1.1b0.dist-info/RECORD
